{"version":{"pluginId":"default","version":"current","label":"Next","banner":null,"badge":false,"noIndex":false,"className":"docs-version-current","isLast":true,"docsSidebars":{"docs":[{"type":"link","href":"/docs/intro","label":"Getting Started","docId":"intro","unlisted":false},{"type":"link","href":"/docs/architecture","label":"Architecture","docId":"architecture","unlisted":false},{"type":"category","label":"Orchestrator","items":[{"type":"link","href":"/docs/orchestrator/memory-orchestrator","label":"Memory Orchestrator","docId":"orchestrator/memory-orchestrator","unlisted":false},{"type":"link","href":"/docs/orchestrator/rag-pipeline","label":"RAG Pipeline","docId":"orchestrator/rag-pipeline","unlisted":false},{"type":"link","href":"/docs/orchestrator/unified-search","label":"Unified Search","docId":"orchestrator/unified-search","unlisted":false},{"type":"link","href":"/docs/orchestrator/session-management","label":"Session Management","docId":"orchestrator/session-management","unlisted":false}],"collapsed":true,"collapsible":true},{"type":"category","label":"Media RAG","items":[{"type":"link","href":"/docs/media/photo-rag","label":"Photo RAG","docId":"media/photo-rag","unlisted":false},{"type":"link","href":"/docs/media/video-rag","label":"Video RAG","docId":"media/video-rag","unlisted":false}],"collapsed":true,"collapsible":true},{"type":"category","label":"WaxCore","items":[{"type":"link","href":"/docs/core/getting-started","label":"Getting Started","docId":"core/getting-started","unlisted":false},{"type":"link","href":"/docs/core/file-format","label":"File Format","docId":"core/file-format","unlisted":false},{"type":"link","href":"/docs/core/wal-crash-recovery","label":"WAL & Crash Recovery","docId":"core/wal-crash-recovery","unlisted":false},{"type":"link","href":"/docs/core/structured-memory","label":"Structured Memory","docId":"core/structured-memory","unlisted":false},{"type":"link","href":"/docs/core/concurrency-model","label":"Concurrency Model","docId":"core/concurrency-model","unlisted":false}],"collapsed":true,"collapsible":true},{"type":"category","label":"Text Search","items":[{"type":"link","href":"/docs/text-search/text-search-engine","label":"Text Search Engine","docId":"text-search/text-search-engine","unlisted":false}],"collapsed":true,"collapsible":true},{"type":"category","label":"Vector Search","items":[{"type":"link","href":"/docs/vector-search/vector-search-engines","label":"Vector Search Engines","docId":"vector-search/vector-search-engines","unlisted":false},{"type":"link","href":"/docs/vector-search/embedding-providers","label":"Embedding Providers","docId":"vector-search/embedding-providers","unlisted":false}],"collapsed":true,"collapsible":true},{"type":"category","label":"MiniLM Embedder","items":[{"type":"link","href":"/docs/mini-lm/mini-lm-embedder","label":"MiniLM Embedder","docId":"mini-lm/mini-lm-embedder","unlisted":false}],"collapsed":true,"collapsible":true}]},"docs":{"architecture":{"id":"architecture","title":"Architecture","description":"Understand the module dependency graph, actor model, and end-to-end data flow.","sidebar":"docs"},"core/concurrency-model":{"id":"core/concurrency-model","title":"Concurrency Model","description":"Understand the actor-per-subsystem architecture, writer leases, and synchronization primitives.","sidebar":"docs"},"core/file-format":{"id":"core/file-format","title":"MV2S File Format","description":"Understand the binary layout of .mv2s files: dual headers, WAL ring buffer, TOC, and footer.","sidebar":"docs"},"core/getting-started":{"id":"core/getting-started","title":"WaxCore Getting Started","description":"Create, open, and interact with .mv2s memory files using the Wax actor.","sidebar":"docs"},"core/structured-memory":{"id":"core/structured-memory","title":"Structured Memory","description":"Store and query knowledge as an entity-fact-predicate graph with bitemporal semantics.","sidebar":"docs"},"core/wal-crash-recovery":{"id":"core/wal-crash-recovery","title":"WAL & Crash Recovery","description":"How the write-ahead log ring buffer ensures durability and enables crash recovery.","sidebar":"docs"},"intro":{"id":"intro","title":"Getting Started","description":"Create a memory orchestrator, remember text, and recall context in minutes.","sidebar":"docs"},"media/photo-rag":{"id":"media/photo-rag","title":"Photo RAG","description":"Build a semantic search layer over photo libraries with OCR, captions, and CLIP embeddings.","sidebar":"docs"},"media/video-rag":{"id":"media/video-rag","title":"Video RAG","description":"Search video content by transcript and visual segments with semantic queries.","sidebar":"docs"},"mini-lm/mini-lm-embedder":{"id":"mini-lm/mini-lm-embedder","title":"MiniLM Embedder","description":"Set up, configure, and optimize the on-device MiniLM embedding provider.","sidebar":"docs"},"orchestrator/memory-orchestrator":{"id":"orchestrator/memory-orchestrator","title":"Memory Orchestrator","description":"Configure and use the primary text RAG orchestrator for ingestion and retrieval.","sidebar":"docs"},"orchestrator/rag-pipeline":{"id":"orchestrator/rag-pipeline","title":"RAG Pipeline","description":"Understand the token-budget-aware context assembly with surrogate tiers and intent-aware reranking.","sidebar":"docs"},"orchestrator/session-management":{"id":"orchestrator/session-management","title":"Session Management","description":"Use WaxSession for read/write multiplexing and understand writer policies.","sidebar":"docs"},"orchestrator/unified-search":{"id":"orchestrator/unified-search","title":"Unified Search","description":"Fuse BM25, vector, structured memory, and timeline results with reciprocal rank fusion.","sidebar":"docs"},"text-search/text-search-engine":{"id":"text-search/text-search-engine","title":"Text Search Engine","description":"Index text, search with BM25 scoring, and manage structured knowledge — all through a single actor.","sidebar":"docs"},"vector-search/embedding-providers":{"id":"vector-search/embedding-providers","title":"Embedding Providers","description":"Implement the TextEmbeddingProvider protocol to supply vector embeddings from any source.","sidebar":"docs"},"vector-search/vector-search-engines":{"id":"vector-search/vector-search-engines","title":"Vector Search Engines","description":"Compare the CPU and GPU backends and understand their performance characteristics.","sidebar":"docs"}}}}